[
  {
    "title": "Команды готовятся к сезону: OVER TIME ZWENIGOROD стартует летом!",
    "image": "https://otz2026.github.io/otz2025/img/NEWS_NO.png",
    "content": "Сезон в лиге OVER TIME ZWENIGOROD начнется только летом, но уже сейчас команды активно тренируются, чтобы показать лучшие результаты на турнире. Игроки отрабатывают тактики, улучшают индивидуальное мастерство и тестируют новые составы – всё ради того, чтобы в ответственных матчах проявить себя на максимум.",
    "full_content": "Сезон в Лиге OVER TIME ZWENIGOROD начнется только летом, но уже сейчас команды активно тренируются, чтобы показать лучшие результаты на турнире. Игроки отрабатывают тактики, улучшают индивидуальное мастерство и тестируют новые составы – всё ради того, чтобы в ответственных матчах проявить себя на максимум. Подготовка в разгаре Тренировочные сборы, скриммы и аналитические разборы стали неотъемлемой частью подготовки команд. Многие коллективы используют перерыв между сезонами, чтобы усилить состав или отточить сыгранность. 1) Тактические новшества – Тренеры и капитаны экспериментируют с новыми стратегиями, чтобы застать соперников врасплох. 2)Физическая и психологическая подготовка – Для стабильной игры важна не только механика, но и выносливость. 3) Тестовые матчи – Команды активно играют друг против друга, чтобы проверить свою готовность.",
    "date": "2025-03-28"
  }
]